{
  "snapshots": [
    {
      "date": "2026-03-27",
      "tvl": 12846934.09,
      "azndApy": 7.51,
      "mubondApy": 12.55,
      "dauLatest": 86,
      "wauLatest": 379,
      "monadSupplies": {
        "AZND": 10490875,
        "MUBOND": 2283428,
        "LOAZND": 822475,
        "SBMU": 16684,
        "AZNDAUSD": 518689,
        "MUBONDAUSD": 240528,
        "CLOAZND": 521662,
        "LOAZNDAZND": 501,
        "CMUBOND": 637283,
        "MTUSD": 13855,
        "NLOAZND": 295045
      }
    },
    {
      "date": "2026-03-27",
      "tvl": 12846934.09,
      "azndApy": 7.51,
      "mubondApy": 12.55,
      "dauLatest": 79,
      "wauLatest": 373,
      "monadSupplies": {
        "AZND": 10490875,
        "MUBOND": 2283428,
        "LOAZND": 822692,
        "CLOAZND": 521662,
        "CMUBOND": 637283,
        "MTUSD": 13855,
        "NLOAZND": 295045,
        "MUBONDAUSD": 240528,
        "AZNDAUSD": 518689,
        "LOAZNDAZND": 501,
        "SBMU": 16684
      }
    },
    {
      "date": "2026-03-27",
      "tvl": 12846934.09,
      "azndApy": 7.51,
      "mubondApy": 12.55,
      "dauLatest": 76,
      "wauLatest": 370,
      "monadSupplies": {
        "AZND": 10490875,
        "MUBOND": 2283428,
        "LOAZND": 822692,
        "CLOAZND": 521662,
        "AZNDAUSD": 518689,
        "CMUBOND": 637283,
        "MTUSD": 13855,
        "MUBONDAUSD": 240528,
        "NLOAZND": 295045,
        "LOAZNDAZND": 501,
        "SBMU": 16684
      }
    },
    {
      "date": "2026-03-27",
      "tvl": 12846934.09,
      "azndApy": 7.36,
      "mubondApy": 12.11,
      "dauLatest": 71,
      "wauLatest": 365,
      "monadSupplies": {
        "AZND": 10490875,
        "MUBOND": 2283428,
        "LOAZND": 822692,
        "CLOAZND": 521662,
        "CMUBOND": 637283,
        "MTUSD": 13855,
        "NLOAZND": 295045,
        "LOAZNDAZND": 501,
        "MUBONDAUSD": 240528,
        "SBMU": 16684,
        "AZNDAUSD": 518689
      }
    },
    {
      "date": "2026-03-27",
      "monadSupplies": {
        "AZND": 10490875,
        "MUBOND": 2283428,
        "LOAZND": 822856,
        "CLOAZND": 521826,
        "CMUBOND": 637383,
        "NLOAZND": 295045,
        "LOAZNDAZND": 501,
        "SBMU": 16684,
        "MTUSD": 13855,
        "AZNDAUSD": 518689,
        "MUBONDAUSD": 240528
      },
      "ethSupplies": {},
      "dauLatest": 58,
      "wauLatest": 357
    },
    {
      "date": "2026-03-27",
      "monadSupplies": {
        "AZND": 10490875,
        "MUBOND": 2283428,
        "LOAZND": 822856,
        "CLOAZND": 521826,
        "CMUBOND": 637383,
        "NLOAZND": 295045,
        "MTUSD": 13855,
        "AZNDAUSD": 518689,
        "MUBONDAUSD": 240528,
        "LOAZNDAZND": 501,
        "SBMU": 16684
      },
      "ethSupplies": {},
      "dauLatest": 49,
      "wauLatest": 351
    },
    {
      "date": "2026-03-27",
      "monadSupplies": {
        "CMUBOND": 637383,
        "NLOAZND": 295045,
        "MTUSD": 13855,
        "AZNDAUSD": 518689,
        "AZND": 10490875,
        "MUBOND": 2283428,
        "LOAZNDAZND": 501,
        "CLOAZND": 521826,
        "LOAZND": 822856,
        "MUBONDAUSD": 240528,
        "SBMU": 16684
      },
      "ethSupplies": {},
      "dauLatest": 48,
      "wauLatest": 351
    }
  ]
}